ics_creator/__init__.py
icsTodoCreator-0.2.dist-info/METADATA
icsTodoCreator-0.2.dist-info/WHEEL
icsTodoCreator-0.2.dist-info/top_level.txt
icsTodoCreator-0.2.dist-info/RECORD
