Metadata-Version: 2.1
Name: icsTodoCreator
Version: 0.2
Summary: A tool to create multiple vcalendar tasks at once to speed up decentralized specialized manufacturing.
Home-page: UNKNOWN
Author: Fabian Becker
Author-email: fab.becker@outlook.de
License: GNU General Public License v3 (GPLv3)
Keywords: ics tasks todo scale MakerVsVirus
Platform: UNKNOWN
Classifier: Development Status :: 3 - Alpha
Classifier: License :: OSI Approved :: GNU General Public License v3 (GPLv3)
Classifier: Programming Language :: Python :: 3.6
